N2G/__init__.py
N2G/plugins/__init__.py
N2G/plugins/data/__init__.py
N2G/plugins/data/cli_ip_data.py
N2G/plugins/data/cli_isis_data.py
N2G/plugins/data/cli_l2_data.py
N2G/plugins/data/cli_ospf_data.py
N2G/plugins/data/json_data.py
N2G/plugins/data/xlsx_data.py
N2G/plugins/diagrams/__init__.py
N2G/plugins/diagrams/N2G_DrawIO.py
N2G/plugins/diagrams/N2G_V3D.py
N2G/plugins/diagrams/N2G_yEd.py
N2G/plugins/viewers/__init__.py
N2G/plugins/viewers/v3d_viewer/__init__.py
N2G/plugins/viewers/v3d_viewer/v3d_viewer.html
N2G/plugins/viewers/v3d_viewer/v3d_viewer.py
N2G/plugins/viewers/yed_viewer/__init__.py
N2G/plugins/viewers/yed_viewer/css/images/ui-icons_444444_256x240.png
N2G/plugins/viewers/yed_viewer/css/images/ui-icons_555555_256x240.png
N2G/plugins/viewers/yed_viewer/css/images/ui-icons_777620_256x240.png
N2G/plugins/viewers/yed_viewer/css/images/ui-icons_777777_256x240.png
N2G/plugins/viewers/yed_viewer/css/images/ui-icons_cc0000_256x240.png
N2G/plugins/viewers/yed_viewer/css/images/ui-icons_ffffff_256x240.png
N2G/plugins/viewers/yed_viewer/css/jquery-ui.css
N2G/plugins/viewers/yed_viewer/css/main.css
N2G/plugins/viewers/yed_viewer/css/select2.min.css
N2G/plugins/viewers/yed_viewer/javascript/d3.v5.js
N2G/plugins/viewers/yed_viewer/javascript/jquery-1.12.4.js
N2G/plugins/viewers/yed_viewer/javascript/jquery-ui-1.12.1.js
N2G/plugins/viewers/yed_viewer/javascript/select2.min.js
N2G/plugins/viewers/yed_viewer/yed_viewer.html
N2G/plugins/viewers/yed_viewer/yed_viewer.py
N2G/utils/__init__.py
N2G/utils/merge_dict.py
N2G/utils/N2G_cli.py
n2g-0.3.2.dist-info/entry_points.txt
n2g-0.3.2.dist-info/LICENSE
n2g-0.3.2.dist-info/WHEEL
n2g-0.3.2.dist-info/METADATA
n2g-0.3.2.dist-info/RECORD
