Metadata-Version: 2.1
Name: n2g
Version: 0.3.2
Summary: Need To Graph
Home-page: https://github.com/dmulyalin/N2G
License: MIT
Keywords: Diagramming,Graphing,Networks
Author: Denis Mulyalin
Author-email: d.mulyalin@gmail.com
Maintainer: Denis Mulyalin
Maintainer-email: d.mulyalin@gmail.com
Requires-Python: >=3.6,<4.0
Classifier: License :: OSI Approved :: MIT License
Classifier: Operating System :: POSIX :: Linux
Classifier: Programming Language :: Python :: 3
Classifier: Programming Language :: Python :: 3.10
Classifier: Programming Language :: Python :: 3.6
Classifier: Programming Language :: Python :: 3.7
Classifier: Programming Language :: Python :: 3.8
Classifier: Programming Language :: Python :: 3.9
Classifier: Topic :: Utilities
Provides-Extra: docs
Provides-Extra: full
Requires-Dist: Sphinx (==4.3.0); (python_version >= "3.7") and (extra == "docs")
Requires-Dist: flask (==2.1.2); (python_version >= "3.7") and (extra == "full")
Requires-Dist: openpyxl (>=3.0.0,<3.1.0); (python_version >= "3.7") and (extra == "full")
Requires-Dist: python-igraph (>=0.9.0,<0.10.0); (python_version >= "3.6") and (extra == "full")
Requires-Dist: readthedocs-sphinx-search (==0.1.1); (python_version >= "3.7") and (extra == "docs")
Requires-Dist: sphinx_rtd_theme (==1.0.0); (python_version >= "3.7") and (extra == "docs")
Requires-Dist: sphinxcontrib-applehelp (==1.0.1); (python_version >= "3.7") and (extra == "docs")
Requires-Dist: sphinxcontrib-devhelp (==1.0.1); (python_version >= "3.7") and (extra == "docs")
Requires-Dist: sphinxcontrib-htmlhelp (==2.0.0); (python_version >= "3.7") and (extra == "docs")
Requires-Dist: sphinxcontrib-jsmath (==1.0.1); (python_version >= "3.7") and (extra == "docs")
Requires-Dist: sphinxcontrib-napoleon (==0.7); (python_version >= "3.7") and (extra == "docs")
Requires-Dist: sphinxcontrib-qthelp (==1.0.2); (python_version >= "3.7") and (extra == "docs")
Requires-Dist: sphinxcontrib-serializinghtml (==1.1.5); (python_version >= "3.7") and (extra == "docs")
Requires-Dist: sphinxcontrib-spelling (==7.2.1); (python_version >= "3.7") and (extra == "docs")
Requires-Dist: ttp (>=0.9.0,<0.10.0); (python_version >= "3.6") and (extra == "full")
Requires-Dist: ttp_templates (>=0.3.0,<0.4.0); (python_version >= "3.6") and (extra == "full")
Project-URL: Documentation, https://n2g.readthedocs.io/
Project-URL: Repository, https://github.com/dmulyalin/N2G
